topdf/__init__.py
topdf/__main__.py
topdf/dl-dt-dd-table.js
topdf/header.html
topdf/main.html
topdf/mkdocs_theme.yml
topdf/topdf.css
topdf/topdf.js
topdf/topdf_extra.css
mkdocs_theme_topdf-0.5.0.dist-info/LICENSE
mkdocs_theme_topdf-0.5.0.dist-info/METADATA
mkdocs_theme_topdf-0.5.0.dist-info/WHEEL
mkdocs_theme_topdf-0.5.0.dist-info/entry_points.txt
mkdocs_theme_topdf-0.5.0.dist-info/top_level.txt
mkdocs_theme_topdf-0.5.0.dist-info/RECORD
