Metadata-Version: 2.1
Name: mkdocs-theme-topdf
Version: 0.5.0
Summary: a mkdocs theme for generate pdf or printing
Home-page: https://github.com/kuri65536/mkdocs-theme-topdf
Author: Shimoda
Author-email: kuri65536@hotmail.com
License: MPL2
Platform: UNKNOWN
